videobench/VideoBench_full.json
videobench/VideoTextAlignment.py
videobench/__init__.py
videobench/dynamicquality.py
videobench/dynamicquality_gridview_customized.py
videobench/prompt_dict.py
videobench/staticquality.py
videobench/staticquality_customized.py
videobench/utils.py
videobench/cli/evaluate.py
videobench/prompt/PromptTemplate4GPTeval.py
videobench/prompt/action.py
videobench/prompt/color.py
videobench/prompt/object_class.py
videobench/prompt/overall_consistency.py
videobench/prompt/scene.py
videobench-0.1.2.dist-info/licenses/LICENSE
videobench-0.1.2.dist-info/METADATA
videobench-0.1.2.dist-info/WHEEL
videobench-0.1.2.dist-info/entry_points.txt
videobench-0.1.2.dist-info/top_level.txt
videobench-0.1.2.dist-info/RECORD
