Metadata-Version: 2.4
Name: videobench
Version: 0.1.2
Summary: Human Preference Aligned Video Generation Benchmark
Project-URL: Source, https://github.com/Video-Bench/Video-Bench
Requires-Python: >=3.8
License-File: LICENSE
Requires-Dist: aiohappyeyeballs==2.3.7
Requires-Dist: aiohttp==3.10.4
Requires-Dist: aiosignal==1.3.1
Requires-Dist: analytics-python==1.4.post1
Requires-Dist: annotated-types==0.7.0
Requires-Dist: anyio==4.4.0
Requires-Dist: astor==0.8.1
Requires-Dist: asttokens
Requires-Dist: async-timeout==4.0.3
Requires-Dist: attrs==24.2.0
Requires-Dist: backoff==1.10.0
Requires-Dist: bcrypt==4.2.0
Requires-Dist: beautifulsoup4==4.12.3
Requires-Dist: certifi
Requires-Dist: cffi==1.16.0
Requires-Dist: charset-normalizer==3.3.2
Requires-Dist: click==8.1.7
Requires-Dist: colorama
Requires-Dist: comm
Requires-Dist: contourpy
Requires-Dist: cryptography==43.0.0
Requires-Dist: cycler
Requires-Dist: Cython==3.0.10
Requires-Dist: debugpy
Requires-Dist: decorator
Requires-Dist: distro==1.9.0
Requires-Dist: et-xmlfile==1.1.0
Requires-Dist: exceptiongroup==1.2.1
Requires-Dist: executing
Requires-Dist: fonttools
Requires-Dist: frozenlist==1.4.1
Requires-Dist: fsspec==2024.6.0
Requires-Dist: h11==0.14.0
Requires-Dist: httpcore==1.0.5
Requires-Dist: httpx==0.27.2
Requires-Dist: idna==3.7
Requires-Dist: imageio==2.34.2
Requires-Dist: imgaug==0.4.0
Requires-Dist: importlib_metadata==8.4.0
Requires-Dist: intel-openmp==2021.4.0
Requires-Dist: ipykernel
Requires-Dist: ipython==8.25.0
Requires-Dist: jedi
Requires-Dist: Jinja2==3.1.4
Requires-Dist: jiter==0.5.0
Requires-Dist: jupyter_client
Requires-Dist: jupyter_core
Requires-Dist: kiwisolver
Requires-Dist: lazy_loader==0.4
Requires-Dist: linkify-it-py==2.0.3
Requires-Dist: lmdb==1.5.1
Requires-Dist: lxml==5.2.2
Requires-Dist: markdown-it-py==3.0.0
Requires-Dist: MarkupSafe==2.1.5
Requires-Dist: matplotlib==3.8.4
Requires-Dist: matplotlib-inline==0.1.7
Requires-Dist: mdit-py-plugins==0.4.1
Requires-Dist: mdurl==0.1.2
Requires-Dist: mkl==2021.4.0
Requires-Dist: mkl-fft
Requires-Dist: mkl-random
Requires-Dist: mkl-service==2.4.0
Requires-Dist: monotonic==1.6
Requires-Dist: mpmath==1.3.0
Requires-Dist: multidict==6.0.5
Requires-Dist: nest_asyncio
Requires-Dist: networkx==3.3
Requires-Dist: ninja==1.11.1.1
Requires-Dist: numpy==1.26.4
Requires-Dist: openai==1.42.0
Requires-Dist: opencv-contrib-python==4.10.0.84
Requires-Dist: opencv-python==4.10.0.84
Requires-Dist: opencv-python-headless==4.10.0.84
Requires-Dist: openpyxl==3.1.5
Requires-Dist: opt-einsum==3.3.0
Requires-Dist: orjson==3.10.7
Requires-Dist: packaging
Requires-Dist: pandas==2.2.2
Requires-Dist: paramiko==3.4.1
Requires-Dist: parso
Requires-Dist: pickleshare
Requires-Dist: pillow==10.3.0
Requires-Dist: platformdirs==4.2.2
Requires-Dist: ply==3.11
Requires-Dist: prompt_toolkit==3.0.47
Requires-Dist: protobuf==3.20.2
Requires-Dist: psutil==6.0.0
Requires-Dist: pure-eval==0.2.2
Requires-Dist: pyclipper==1.3.0.post5
Requires-Dist: pycparser==2.22
Requires-Dist: pycryptodome==3.20.0
Requires-Dist: pydantic==2.7.4
Requires-Dist: pydantic_core==2.18.4
Requires-Dist: pydub==0.25.1
Requires-Dist: pygments==2.18.0
Requires-Dist: PyNaCl==1.5.0
Requires-Dist: pyparsing==3.0.9
Requires-Dist: python-bidi==0.5.1
Requires-Dist: python-dateutil==2.9.0
Requires-Dist: python-docx==1.1.2
Requires-Dist: python-multipart==0.0.9
Requires-Dist: pytz==2024.1
Requires-Dist: pywin32==306
Requires-Dist: pyzmq==26.2.0
Requires-Dist: rapidfuzz==3.9.4
Requires-Dist: requests==2.32.3
Requires-Dist: rfc3986==1.5.0
Requires-Dist: scikit-image==0.24.0
Requires-Dist: scipy==1.14.0
Requires-Dist: shapely==2.0.5
Requires-Dist: sip==6.7.12
Requires-Dist: six==1.16.0
Requires-Dist: sniffio==1.3.1
Requires-Dist: soupsieve==2.5
Requires-Dist: stack-data==0.6.3
Requires-Dist: starlette==0.38.2
Requires-Dist: sympy==1.12.1
Requires-Dist: tbb==2021.13.0
Requires-Dist: tenacity==8.4.2
Requires-Dist: termcolor==2.4.0
Requires-Dist: tifffile==2024.7.24
Requires-Dist: tomli==2.0.1
Requires-Dist: tornado==6.4.1
Requires-Dist: tqdm==4.66.4
Requires-Dist: traitlets==5.14.3
Requires-Dist: typing_extensions==4.12.2
Requires-Dist: tzdata==2024.1
Requires-Dist: uc-micro-py==1.0.3
Requires-Dist: unicodedata2==15.1.0
Requires-Dist: urllib3==2.2.2
Requires-Dist: uvicorn==0.30.6
Requires-Dist: wcwidth==0.2.13
Requires-Dist: wincertstore==0.2
Requires-Dist: xlrd==2.0.1
Requires-Dist: yarl==1.9.4
Requires-Dist: zipp==3.20.1
Dynamic: description
Dynamic: description-content-type
Dynamic: license-file
Dynamic: project-url
Dynamic: requires-dist
Dynamic: requires-python
Dynamic: summary
